ngsfragments/.DS_Store
ngsfragments/__init__.py
ngsfragments/config.py
ngsfragments/correct/__init__.py
ngsfragments/correct/correct_intervals.py
ngsfragments/correct/correction.py
ngsfragments/correct/cylowess/__init__.py
ngsfragments/correct/cylowess/cylowess.c
ngsfragments/correct/cylowess/cylowess.pyx
ngsfragments/coverage/__init__.py
ngsfragments/coverage/coverage.py
ngsfragments/coverage/midpoint.py
ngsfragments/coverage/wps.py
ngsfragments/fragments.py
ngsfragments/io/__init__.py
ngsfragments/io/parse_fragments/read_fragments.c
ngsfragments/io/parse_fragments/read_fragments.h
ngsfragments/io/parse_sam/ReadSam.c
ngsfragments/io/parse_sam/ReadSam.pxd
ngsfragments/io/parse_sam/ReadSam.pyx
ngsfragments/io/parse_sam/__init__.py
ngsfragments/io/parse_sam/merge_bams.c
ngsfragments/io/parse_sam/methyl_fragment_iter.c
ngsfragments/io/parse_sam/methyl_record.c
ngsfragments/io/parse_sam/methyl_size_split.c
ngsfragments/io/parse_sam/read_intervals.c
ngsfragments/io/parse_sam/read_intervals.h
ngsfragments/io/parse_sam/read_iterator.c
ngsfragments/io/parse_sam/read_name_store.c
ngsfragments/io/parse_sam/reference_methyl.c
ngsfragments/io/read_fragments.py
ngsfragments/io/read_sam.py
ngsfragments/metrics/__init__.py
ngsfragments/metrics/coverage_metrics.py
ngsfragments/metrics/gc_metrics.py
ngsfragments/metrics/gene_activity.py
ngsfragments/metrics/metric_utils.py
ngsfragments/metrics/tf_site_coverage.py
ngsfragments/metrics/wps_metrics.py
ngsfragments/peak_calling/CallPeaks.c
ngsfragments/peak_calling/CallPeaks.pxd
ngsfragments/peak_calling/CallPeaks.pyx
ngsfragments/peak_calling/RunningMean.c
ngsfragments/peak_calling/RunningMean.pxd
ngsfragments/peak_calling/RunningMean.pyx
ngsfragments/peak_calling/RunningMedian.c
ngsfragments/peak_calling/RunningMedian.pxd
ngsfragments/peak_calling/RunningMedian.pyx
ngsfragments/peak_calling/__init__.py
ngsfragments/peak_calling/running_mean.c
ngsfragments/peak_calling/running_mean.h
ngsfragments/peak_calling/sklist_pd.c
ngsfragments-2.5.3.dist-info/METADATA
ngsfragments-2.5.3.dist-info/WHEEL
ngsfragments-2.5.3.dist-info/licenses/LICENSE.md
ngsfragments-2.5.3.dist-info/RECORD
